CHANGES.txt
LICENSE.txt
MANIFEST.in
README.txt
setup.py
js/__init__.py
js.d3_tip.egg-info/PKG-INFO
js.d3_tip.egg-info/SOURCES.txt
js.d3_tip.egg-info/dependency_links.txt
js.d3_tip.egg-info/entry_points.txt
js.d3_tip.egg-info/namespace_packages.txt
js.d3_tip.egg-info/not-zip-safe
js.d3_tip.egg-info/requires.txt
js.d3_tip.egg-info/top_level.txt
js/d3_tip/__init__.py
js/d3_tip/test_d3-tip.txt
js/d3_tip/resources/d3_tip.js