Metadata-Version: 1.0
Name: js.d3-tip
Version: 0.6.7
Summary: Fanstatic packaging of d3-tip
Home-page: UNKNOWN
Author: Fanstatic Developers
Author-email: fanstatic@googlegroups.com
License: BSD
Platform: UNKNOWN
